asynctb/__init__.py
asynctb/_frame_tricks_cpython.py
asynctb/_frame_tricks_pypy.py
asynctb/_frames.py
asynctb/_glue.py
asynctb/_registry.py
asynctb/_traceback.py
asynctb/_version.py
asynctb/py.typed
asynctb/_tests/__init__.py
asynctb/_tests/conftest.py
asynctb/_tests/test_frames.py
asynctb/_tests/test_registry.py
asynctb/_tests/test_traceback.py
asynctb-0.0.0a0.dist-info/LICENSE
asynctb-0.0.0a0.dist-info/LICENSE.APACHE2
asynctb-0.0.0a0.dist-info/LICENSE.MIT
asynctb-0.0.0a0.dist-info/METADATA
asynctb-0.0.0a0.dist-info/WHEEL
asynctb-0.0.0a0.dist-info/top_level.txt
asynctb-0.0.0a0.dist-info/RECORD
