Metadata-Version: 2.1
Name: asynctb
Version: 0.0.0a0
Summary: Traceback utilities for async programming in Python
Home-page: https://github.com/oremanj/asynctb
Author: Joshua Oreman
Author-email: oremanj@gmail.com
License: MIT -or- Apache License 2.0
Keywords: async,debugging,trio,asyncio
Platform: UNKNOWN
Classifier: License :: OSI Approved :: MIT License
Classifier: License :: OSI Approved :: Apache Software License
Classifier: Operating System :: POSIX :: Linux
Classifier: Operating System :: MacOS :: MacOS X
Classifier: Operating System :: Microsoft :: Windows
Classifier: Programming Language :: Python :: 3 :: Only
Classifier: Programming Language :: Python :: Implementation :: CPython
Classifier: Programming Language :: Python :: Implementation :: PyPy
Classifier: Development Status :: 3 - Alpha
Classifier: Intended Audience :: Developers
Requires-Python: >=3.6
License-File: LICENSE
License-File: LICENSE.APACHE2
License-File: LICENSE.MIT
Requires-Dist: attrs (>=19.2)
